[{"title":"小黄人大眼萌 Minions (2015)","name":"Minions.2015.1080p.BluRay.H264.AAC-RARBG","score":"","size":"1.74GB","date":"01-15","format":"BluRay-1080P","fileTree":"\n      Minions.2015.1080p.BluRay.H264.AAC-RARBG\n       Subs Minions.2015.1080p.BluRay.H264.AAC-RARBG.idx(75KB) Minions.2015.1080p.BluRay.H264.AAC-RARBG.sub(3.96MB) Minions.2015.1080p.BluRay.H264.AAC-RARBG.mp4(1.73GB) PianYuan.net.txt(30B)      ","magnet":"magnet:?xt=urn:btih:05766e0703f7bbcd5a498879085baca92b56471c&dn=Minions.2015.1080p.BluRay.H264.AAC-RARBG&tr=http%3A%2F%2Ftracker.trackerfix.com%3A80%2Fannounce&tr=udp%3A%2F%2F9.rarbg.me%3A2710%2Fannounce&tr=udp%3A%2F%2F9.rarbg.to%3A2710%2Fannounce","img":"/Uploads/Picture/litpic/08/26Aug2015113701.jpg"},{"title":"神偷奶爸2 Despicable Me 2 (2013)","name":"Despicable.Me.2.2013.1080p.BluRay.x264.DTS-X.7.1-SWTYBLZ","score":"","size":"8.72GB","date":"12-25","format":"BluRay-1080P","fileTree":"\n      Despicable.Me.2.2013.1080p.BluRay.x264.DTS-X.7.1-SWTYBLZ\n       Despicable.Me.2.2013.1080p.BluRay.x264.DTS-X.7.1-SWTYBLZ.mkv(8.72GB) PianYuan.net.txt(31B)      ","magnet":"magnet:?xt=urn:btih:edf83b06eba774dddba4628bb6839d9b5a6325fd&dn=Despicable.Me.2.2013.1080p.BluRay.x264.DTS-X.7.1-SWTYBLZ&tr=http%3A%2F%2Ftracker.trackerfix.com%3A80%2Fannounce&tr=udp%3A%2F%2F9.rarbg.me%3A2710%2Fannounce&tr=udp%3A%2F%2F9.rarbg.to%3A2710%2Fannounce","img":"/Uploads/Picture/litpic/07/20Jul2015135811.jpg"},{"title":"Unmasking Jihadi John Anatomy of a Terrorist Unmasking Jihadi John Anatomy of a Terrorist (2019)","name":"Unmasking.Jihadi.John.Anatomy.of.a.Terrorist.2019.1080p.AMZN.WEBRip.DDP2.0.x264-NTG","score":"","size":"6.66GB","date":"08-02","format":"WEB-1080P","fileTree":"\n      Unmasking.Jihadi.John.Anatomy.of.a.Terrorist.2019.1080p.AMZN.WEBRip.DDP2.0.x264-NTG\n       PianYuan.net.txt(31B) Unmasking.Jihadi.John.Anatomy.of.a.Terrorist.2019.1080p.AMZN.WEB-DL.DDP2.0.H.264-NTG.mkv(6.66GB)      ","magnet":"magnet:?xt=urn:btih:c608b2ed866c7bcea8c5d3d60b29524fe2efc1d0&dn=Unmasking.Jihadi.John.Anatomy.of.a.Terrorist.2019.1080p.AMZN.WEBRip.DDP2.0.x264-NTG&tr=http%3A%2F%2Ftracker.trackerfix.com%3A80%2Fannounce&tr=udp%3A%2F%2F9.rarbg.me%3A2760%2Fannounce&tr=udp%3A%2F%2F9.rarbg.to%3A2730%2Fannounce","img":"/Uploads/Picture/litpic/08/02Aug2019103458.jpg"},{"title":"沙达 Shadaa (2019)","name":"Shadaa 2019 1080p Punjabi AMZN WEBRip x264 DD 5.1 ESubs - LOKiHD - Telly","score":"","size":"3.21GB","date":"08-02","format":"WEB-1080P","fileTree":"\n      Shadaa 2019 1080p Punjabi AMZN WEBRip x264 DD 5.1 ESubs - LOKiHD - Telly\n       SaMple.mkv(27.54MB) Shadaa 2019 1080p Punjabi AMZN WEBRip x264 DD 5.1 ESubs - LOKiHD - Telly.mkv(3.19GB) PianYuan.net.txt(190B)      ","magnet":"magnet:?xt=urn:btih:a0a48cb408576235bdddc99e97d4511a080d68d8&dn=Shadaa+2019+1080p+Punjabi+AMZN+WEBRip+x264+DD+5.1+ESubs+-+LOKiHD+-+Telly&tr=udp%3A%2F%2Ftracker.coppersurfer.tk%3A6969%2Fannounce&tr=udp%3A%2F%2Ftracker.leechers-paradise.org%3A6969%2Fannounce&tr=udp%3A%2F%2Fopen.stealth.si%3A80%2Fannounce","img":"/Uploads/Picture/litpic/08/02Aug2019102856.jpg"},{"title":"一条狗的回家路 A Dog's Way Home (2019)","name":"A Dogs Way Home 2019 1080p AMZN WEBRip Hindi English x264 DD 5.1 ESubs - LOKiHD - Telly","score":"","size":"3.02GB","date":"08-02","format":"WEB-1080P","fileTree":"\n      A Dogs Way Home 2019 1080p AMZN WEBRip Hindi English x264 DD 5.1 ESubs - LOKiHD - Telly\n       A Dogs Way Home 2019 1080p AMZN WEBRip Hindi English x264 DD 5.1 ESubs - LOKiHD - Telly.mkv(3GB) SaMple.mkv(18.83MB) PianYuan.net.txt(190B)      ","magnet":"magnet:?xt=urn:btih:54abc78f3a83a6bc0ed60aa21ffca130520d456a&dn=A+Dogs+Way+Home+2019+1080p+AMZN+WEBRip+Hindi+English+x264+DD+5.1+ESubs+-+LOKiHD+-+Telly&tr=udp%3A%2F%2Ftracker.coppersurfer.tk%3A6969%2Fannounce&tr=udp%3A%2F%2Ftracker.leechers-paradise.org%3A6969%2Fannounce&tr=udp%3A%2F%2Fopen.stealth.si%3A80%2Fannounce","img":"/Uploads/Picture/litpic/03/21Mar2019002244.jpg"},{"title":"The Healer The Healer (2017)","name":"The.Healer.2017.1080p.BluRay.x264-RUSTED","score":"","size":"7.64GB","date":"12-25","format":"BluRay-1080P","fileTree":"\n      The.Healer.2017.1080p.BluRay.x264-RUSTED\n       PianYuan.net.txt(30B) the.healer.2017.1080p.bluray.x264-rusted.jpg(5.7KB) the.healer.2017.1080p.bluray.x264-rusted.mkv(7.64GB) the.healer.2017.1080p.bluray.x264-rusted.nfo(9.2KB)      ","magnet":"magnet:?xt=urn:btih:11bcaa63b531a43cb8ef05e08b435c7b818f2c9a&dn=The.Healer.2017.1080p.BluRay.x264-RUSTED&tr=http%3A%2F%2Ftracker.trackerfix.com%3A80%2Fannounce&tr=udp%3A%2F%2F9.rarbg.me%3A2710%2Fannounce&tr=udp%3A%2F%2F9.rarbg.to%3A2710%2Fannounce","img":"/Uploads/Picture/litpic/12/25Dec2017140056.jpg"},{"title":"墨西哥裔美国人 El Chicano (2019)","name":"El.Chicano.2018.1080p.BluRay.x264.DTS-HD.MA.5.1-FGT","score":"","size":"10.26GB","date":"07-30","format":"BluRay-1080P","fileTree":"\n      El.Chicano.2018.1080p.BluRay.x264.DTS-HD.MA.5.1-FGT\n       El.Chicano.2018.1080p.BluRay.x264.DTS-HD.MA.5.1-FGT.mkv(10.26GB) PianYuan.net.txt(31B)      ","magnet":"magnet:?xt=urn:btih:1474060c4e5113dde5ad1a69258fa02bf015cad0&dn=El.Chicano.2018.1080p.BluRay.x264.DTS-HD.MA.5.1-FGT&tr=http%3A%2F%2Ftracker.trackerfix.com%3A80%2Fannounce&tr=udp%3A%2F%2F9.rarbg.me%3A2730%2Fannounce&tr=udp%3A%2F%2F9.rarbg.to%3A2720%2Fannounce","img":"/Uploads/Picture/litpic/07/22Jul2019091845.jpg"},{"title":"金蝉脱壳3：恶魔车站 Escape Plan: The Extractors (2019)","name":"Escape Plan-The Extractors (2019)-alE13","score":"","size":"9.67GB","date":"08-02","format":"BluRay-1080P","fileTree":"\n      Escape Plan-The Extractors (2019)-alE13\n       Subtitles Escape Plan-The Extractors (2019)-alE13.rar(963.87KB) info The Action Elite.png(438.14KB) Nostalgie.jpg(185.84KB) PianYuan.net.txt(270B) PianYuan.net.txt(61B) PianYuan.net.txt(48B) PianYuan.net.txt(46B) PianYuan.net.txt(44B) PianYuan.net.txt(44B) PianYuan.net.txt(43B) PianYuan.net.txt(42B) Escape Plan-The Extractors (2019)-alE13.mkv(7.82GB) Escape Plan-The Extractors (2019)-alE13.mka(1.75GB) Sample.mkv(101.91MB) Poster.jpg(123.39KB) txt.jpg(104.62KB)      ","magnet":"magnet:?xt=urn:btih:53b233d2d9527e418c4e9dd58c6c9ae5c63a2f48&dn=Escape+Plan-The+Extractors+%282019%29-alE13&tr=udp%3A%2F%2Ftracker.coppersurfer.tk%3A6969%2Fannounce&tr=udp%3A%2F%2Ftracker.leechers-paradise.org%3A6969%2Fannounce&tr=udp%3A%2F%2Ftracker.coppersurfer.tk%3A6969%2Fannounce","img":"/Uploads/Picture/litpic/06/23Jun2019012608.jpg"},{"title":"开心与难过微不足道的时刻 Momenti di trascurabile felicità e infelicità (2019)","name":"Momenti.di.trascurabile.felicita.2019.ITALIAN.1080p.BluRay.H264.AAC-VXT","score":"","size":"1.79GB","date":"08-01","format":"BluRay-1080P","fileTree":"\n      Momenti.di.trascurabile.felicita.2019.ITALIAN.1080p.BluRay.H264.AAC-VXT\n       Subs 2_English.srt(74.78KB) Momenti.di.trascurabile.felicita.2019.ITALIAN.1080p.BluRay.H264.AAC-VXT.mp4(1.79GB) PianYuan.net.txt(30B) RARBG_DO_NOT_MIRROR.exe(99B)      ","magnet":"magnet:?xt=urn:btih:7a23da4e706b598ed18ded3b037172cb8ecf46b6&dn=Momenti.di.trascurabile.felicita.2019.ITALIAN.1080p.BluRay.H264.AAC-VXT&tr=http%3A%2F%2Ftracker.trackerfix.com%3A80%2Fannounce&tr=udp%3A%2F%2F9.rarbg.me%3A2770%2Fannounce&tr=udp%3A%2F%2F9.rarbg.to%3A2750%2Fannounce","img":"/Uploads/Picture/litpic/07/31Jul2019114946.jpg"},{"title":"河流和城墙 The River and the Wall (2019)","name":"The.River.and.the.Wall.2019.1080p.BluRay.x264-HANDJOB","score":"","size":"7.06GB","date":"08-01","format":"BluRay-1080P","fileTree":"\n      The.River.and.the.Wall.2019.1080p.BluRay.x264-HANDJOB\n       PianYuan.net.txt(31B) The.River.and.the.Wall.2019.1080p.BluRay.x264-HANDJOB.mkv(7.06GB)      ","magnet":"magnet:?xt=urn:btih:fa10e0e8f9df39cae8c97ef9ee08819707133248&dn=The.River.and.the.Wall.2019.1080p.BluRay.x264-HANDJOB&tr=http%3A%2F%2Ftracker.trackerfix.com%3A80%2Fannounce&tr=udp%3A%2F%2F9.rarbg.me%3A2750%2Fannounce&tr=udp%3A%2F%2F9.rarbg.to%3A2770%2Fannounce","img":"/Uploads/Picture/litpic/08/01Aug2019103324.jpg"},{"title":"橘子酱男孩 ママレード・ボーイ (2018)","name":"Marmalade.Boy.2018.JAPANESE.1080p.BluRay.H264.AAC-VXT","score":"","size":"2.43GB","date":"08-01","format":"BluRay-1080P","fileTree":"\n      Marmalade.Boy.2018.JAPANESE.1080p.BluRay.H264.AAC-VXT\n       Subs 2_English.srt(76.61KB) Marmalade.Boy.2018.JAPANESE.1080p.BluRay.H264.AAC-VXT.mp4(2.43GB) PianYuan.net.txt(30B) RARBG_DO_NOT_MIRROR.exe(99B)      ","magnet":"magnet:?xt=urn:btih:19c8c199c5cde530854e4a1d277f74bbfe1d3c03&dn=Marmalade.Boy.2018.JAPANESE.1080p.BluRay.H264.AAC-VXT&tr=http%3A%2F%2Ftracker.trackerfix.com%3A80%2Fannounce&tr=udp%3A%2F%2F9.rarbg.me%3A2780%2Fannounce&tr=udp%3A%2F%2F9.rarbg.to%3A2750%2Fannounce","img":"/Uploads/Picture/litpic/09/24Sep2018074311.jpg"},{"title":"红海潜水俱乐部 The Red Sea Diving Resort (2019)","name":"The.Red.Sea.Diving.Resort.2019.1080p.NF.WEB-DL.DDP5.1.H264-CMRG[TGx]","score":"","size":"4.77GB","date":"08-01","format":"WEB-1080P","fileTree":"\n      The.Red.Sea.Diving.Resort.2019.1080p.NF.WEB-DL.DDP5.1.H264-CMRG[TGx]\n       The.Red.Sea.Diving.Resort.2019.1080p.NF.WEB-DL.DDP5.1.H264-CMRG.mkv(4.77GB) The.Red.Sea.Diving.Resort.2019.1080p.NF.WEB-DL.DDP5.1.H264-CMRG.nfo(2.74KB) PianYuan.net.txt(689B)      ","magnet":"magnet:?xt=urn:btih:d5624a25708d26268faf0089468e1c31e162d624&dn=The.Red.Sea.Diving.Resort.2019.1080p.NF.WEB-DL.DDP5.1.H264-CMRG%5BTGx%5D&tr=udp%3A%2F%2Ftracker.coppersurfer.tk%3A6969%2Fannounce&tr=udp%3A%2F%2Ftracker.leechers-paradise.org%3A6969%2Fannounce&tr=udp%3A%2F%2Fbt.xxx-tracker.com%3A2710%2Fannounce","img":"/Uploads/Picture/litpic/07/31Jul2019211943.jpg"},{"title":"库尔斯克 Kursk (2018)","name":"The.Command.2018.1080p.BluRay.x264-GECKOS[TGx]","score":"","size":"8.76GB","date":"08-01","format":"BluRay-1080P","fileTree":"\n      The.Command.2018.1080p.BluRay.x264-GECKOS[TGx]\n       Proof the.command.2018.1080p.bluray.x264-geckos.proof.jpg(2.13MB) Sample the.command.2018.1080p.bluray.x264-geckos.sample.mkv(8.19MB) Subs the.command.2018.1080p.bluray.x264-geckos.subs.sfv(61B) The.Command.2018.1080p.BluRay.x264-GECKOS.mkv(8.75GB) PianYuan.net.txt(689B) the.command.2018.1080p.bluray.x264-geckos.jpg(200.88KB) the.command.2018.1080p.bluray.x264-geckos.nfo(3.24KB) the.command.2018.1080p.bluray.x264-geckos.sfv(5.14KB)      ","magnet":"magnet:?xt=urn:btih:e40b97b46f841bb01b2222c811d44868805d548a&dn=The.Command.2018.1080p.BluRay.x264-GECKOS%5BTGx%5D&tr=udp%3A%2F%2Ftracker.coppersurfer.tk%3A6969%2Fannounce&tr=udp%3A%2F%2Ftracker.leechers-paradise.org%3A6969%2Fannounce&tr=udp%3A%2F%2Fbt.xxx-tracker.com%3A2710%2Fannounce","img":"/Uploads/Picture/litpic/02/20Feb2019185329.jpg"},{"title":"蝴蝶效应3：启示 The Butterfly Effect 3: Revelations (2009)","name":"The.Butterfly.Effect.3.Revelations.2009.PROPER.1080p.BluRay.H264.AAC-RARBG","score":"","size":"1.72GB","date":"4天前","format":"BluRay-1080P","fileTree":"\n      The.Butterfly.Effect.3.Revelations.2009.PROPER.1080p.BluRay.H264.AAC-RARBG\n       Subs 2_English.srt(72.14KB) PianYuan.net.txt(30B) RARBG_DO_NOT_MIRROR.exe(99B) The.Butterfly.Effect.3.Revelations.2009.PROPER.1080p.BluRay.H264.AAC-RARBG.mp4(1.72GB)      ","magnet":"magnet:?xt=urn:btih:2ba60950d2f811a3b5412244d720c2cbafc9e12a&dn=The.Butterfly.Effect.3.Revelations.2009.PROPER.1080p.BluRay.H264.AAC-RARBG&tr=http%3A%2F%2Ftracker.trackerfix.com%3A80%2Fannounce&tr=udp%3A%2F%2F9.rarbg.me%3A2750%2Fannounce&tr=udp%3A%2F%2F9.rarbg.to%3A2730%2Fannounce","img":"/Uploads/Picture/litpic/07/22Jul2015034816.jpg"},{"title":"致命化身 Mary Reilly (1996)","name":"Mary.Reilly.1996.1080p.BluRay.H264.AAC-RARBG","score":"","size":"2.07GB","date":"02-27","format":"BluRay-1080P","fileTree":"\n      Mary.Reilly.1996.1080p.BluRay.H264.AAC-RARBG\n       Subs 2_English.srt(58.01KB) Mary.Reilly.1996.1080p.BluRay.H264.AAC-RARBG.idx(36.64KB) Mary.Reilly.1996.1080p.BluRay.H264.AAC-RARBG.sub(5.34MB) Mary.Reilly.1996.1080p.BluRay.H264.AAC-RARBG.mp4(2.07GB) PianYuan.net.txt(30B) RARBG_DO_NOT_MIRROR.exe(99B)      ","magnet":"magnet:?xt=urn:btih:0ff638aa1312edad433b268d876d03b2c735ec49&dn=Mary.Reilly.1996.1080p.BluRay.H264.AAC-RARBG&tr=http%3A%2F%2Ftracker.trackerfix.com%3A80%2Fannounce&tr=udp%3A%2F%2F9.rarbg.me%3A2710%2Fannounce&tr=udp%3A%2F%2F9.rarbg.to%3A2710%2Fannounce","img":"/Uploads/Picture/litpic/08/24Aug2015204548.jpg"},{"title":"春逝 봄날은간다 (2001)","name":"One.Fine.Spring.Day.2001.PROPER.KOREAN.1080p.BluRay.H264.AAC-VXT","score":"","size":"2.19GB","date":"4天前","format":"BluRay-1080P","fileTree":"\n      One.Fine.Spring.Day.2001.PROPER.KOREAN.1080p.BluRay.H264.AAC-VXT\n       Subs 2_English.srt(30.9KB) One.Fine.Spring.Day.2001.PROPER.KOREAN.1080p.BluRay.H264.AAC-VXT.mp4(2.19GB) PianYuan.net.txt(30B) RARBG_DO_NOT_MIRROR.exe(99B)      ","magnet":"magnet:?xt=urn:btih:b8f6f9ac64472dbe5e566161f192813dd5fb624a&dn=One.Fine.Spring.Day.2001.PROPER.KOREAN.1080p.BluRay.H264.AAC-VXT&tr=http%3A%2F%2Ftracker.trackerfix.com%3A80%2Fannounce&tr=udp%3A%2F%2F9.rarbg.me%3A2750%2Fannounce&tr=udp%3A%2F%2F9.rarbg.to%3A2720%2Fannounce","img":"/Uploads/Picture/litpic/07/20Jul2015192529.jpg"},{"title":"狮口惊魂 Prey (2007)","name":"Prey.2007.1080p.BluRay.x264.DD5.1-FGT","score":"","size":"6.31GB","date":"4天前","format":"BluRay-1080P","fileTree":"\n      Prey.2007.1080p.BluRay.x264.DD5.1-FGT\n       Prey.2007.1080p.BluRay.x264.DD5.1-FGT.mkv(6.31GB) PianYuan.net.txt(31B)      ","magnet":"magnet:?xt=urn:btih:df79b5310b89b72a679e6b8f42ae40eccd138c5a&dn=Prey.2007.1080p.BluRay.x264.DD5.1-FGT&tr=http%3A%2F%2Ftracker.trackerfix.com%3A80%2Fannounce&tr=udp%3A%2F%2F9.rarbg.me%3A2750%2Fannounce&tr=udp%3A%2F%2F9.rarbg.to%3A2720%2Fannounce","img":"/Uploads/Picture/litpic/07/23Jul2015085555.jpg"},{"title":"峡谷深处 Deep in the Valley (2009)","name":"Deep.In.The.Valley.2009.PROPER.1080p.BluRay.H264.AAC-RARBG","score":"","size":"1.66GB","date":"4天前","format":"BluRay-1080P","fileTree":"\n      Deep.In.The.Valley.2009.PROPER.1080p.BluRay.H264.AAC-RARBG\n       Deep.In.The.Valley.2009.PROPER.1080p.BluRay.H264.AAC-RARBG.mp4(1.66GB) PianYuan.net.txt(30B) RARBG_DO_NOT_MIRROR.exe(99B)      ","magnet":"magnet:?xt=urn:btih:88c106a610f9d9d83989a8610f97de04c23767c8&dn=Deep.In.The.Valley.2009.PROPER.1080p.BluRay.H264.AAC-RARBG&tr=http%3A%2F%2Ftracker.trackerfix.com%3A80%2Fannounce&tr=udp%3A%2F%2F9.rarbg.me%3A2720%2Fannounce&tr=udp%3A%2F%2F9.rarbg.to%3A2760%2Fannounce","img":"/Uploads/Picture/litpic/07/22Jul2015204923.jpg"},{"title":"公园里的女孩 The Girl in the Park (2007)","name":"The.Girl.In.The.Park.2007.PROPER.1080p.BluRay.H264.AAC-RARBG","score":"","size":"2.02GB","date":"4天前","format":"BluRay-1080P","fileTree":"\n      The.Girl.In.The.Park.2007.PROPER.1080p.BluRay.H264.AAC-RARBG\n       PianYuan.net.txt(30B) RARBG_DO_NOT_MIRROR.exe(99B) The.Girl.In.The.Park.2007.PROPER.1080p.BluRay.H264.AAC-RARBG.mp4(2.02GB)      ","magnet":"magnet:?xt=urn:btih:068c29e4dc7878d9c5a892ecb288eff5d3cfa9d1&dn=The.Girl.In.The.Park.2007.PROPER.1080p.BluRay.H264.AAC-RARBG&tr=http%3A%2F%2Ftracker.trackerfix.com%3A80%2Fannounce&tr=udp%3A%2F%2F9.rarbg.me%3A2720%2Fannounce&tr=udp%3A%2F%2F9.rarbg.to%3A2730%2Fannounce","img":"/Uploads/Picture/litpic/07/22Jul2015080137.jpg"},{"title":"最后的请求 The Last Request (2006)","name":"The.Last.Request.2006.PROPER.1080p.BluRay.H264.AAC-RARBG","score":"","size":"1.75GB","date":"4天前","format":"BluRay-1080P","fileTree":"\n      The.Last.Request.2006.PROPER.1080p.BluRay.H264.AAC-RARBG\n       PianYuan.net.txt(30B) RARBG_DO_NOT_MIRROR.exe(99B) The.Last.Request.2006.PROPER.1080p.BluRay.H264.AAC-RARBG.mp4(1.75GB)      ","magnet":"magnet:?xt=urn:btih:a36b813f28f10c18482737436ed0b267cc8f4b9b&dn=The.Last.Request.2006.PROPER.1080p.BluRay.H264.AAC-RARBG&tr=http%3A%2F%2Ftracker.trackerfix.com%3A80%2Fannounce&tr=udp%3A%2F%2F9.rarbg.me%3A2720%2Fannounce&tr=udp%3A%2F%2F9.rarbg.to%3A2780%2Fannounce","img":"/Uploads/Picture/litpic/07/24Jul2015082707.jpg"},{"title":"冲浪英豪 Chasing Mavericks (2012)","name":"Chasing.Mavericks.2012.PROPER.1080p.BluRay.H264.AAC-RARBG","score":"","size":"2.22GB","date":"4天前","format":"BluRay-1080P","fileTree":"\n      Chasing.Mavericks.2012.PROPER.1080p.BluRay.H264.AAC-RARBG\n       Subs 2_English.srt(85.44KB) Chasing.Mavericks.2012.PROPER.1080p.BluRay.H264.AAC-RARBG.mp4(2.22GB) PianYuan.net.txt(30B) RARBG_DO_NOT_MIRROR.exe(99B)      ","magnet":"magnet:?xt=urn:btih:ccee4f3c15aba963daa105a4337aa05f9c409740&dn=Chasing.Mavericks.2012.PROPER.1080p.BluRay.H264.AAC-RARBG&tr=http%3A%2F%2Ftracker.trackerfix.com%3A80%2Fannounce&tr=udp%3A%2F%2F9.rarbg.me%3A2750%2Fannounce&tr=udp%3A%2F%2F9.rarbg.to%3A2760%2Fannounce","img":"/Uploads/Picture/litpic/07/20Jul2015173242.jpg"},{"title":"卡里加里博士的小屋 Das Cabinet des Dr. Caligari (1920)","name":"The.Cabinet.Of.Dr.Caligari.1920.GERMAN.1080p.BluRay.H264.AAC-VXT","score":"","size":"1.47GB","date":"4天前","format":"BluRay-1080P","fileTree":"\n      The.Cabinet.Of.Dr.Caligari.1920.GERMAN.1080p.BluRay.H264.AAC-VXT\n       Subs 2_English.srt(9.32KB) PianYuan.net.txt(30B) RARBG_DO_NOT_MIRROR.exe(99B) The.Cabinet.Of.Dr.Caligari.1920.GERMAN.1080p.BluRay.H264.AAC-VXT.mp4(1.47GB)      ","magnet":"magnet:?xt=urn:btih:2b8b5b9c81f9a4bc4c4ffb88d171ad853100734f&dn=The.Cabinet.Of.Dr.Caligari.1920.GERMAN.1080p.BluRay.H264.AAC-VXT&tr=http%3A%2F%2Ftracker.trackerfix.com%3A80%2Fannounce&tr=udp%3A%2F%2F9.rarbg.me%3A2750%2Fannounce&tr=udp%3A%2F%2F9.rarbg.to%3A2770%2Fannounce","img":"/Uploads/Picture/litpic/07/24Jul2015125124.jpg"},{"title":"贝德福德军变 The Bedford Incident (1965)","name":"The.Bedford.Incident.1965.1080p.BluRay.H264.AAC-RARBG","score":"","size":"1.95GB","date":"06-29","format":"BluRay-1080P","fileTree":"\n      The.Bedford.Incident.1965.1080p.BluRay.H264.AAC-RARBG\n       PianYuan.net.txt(30B) RARBG_DO_NOT_MIRROR.exe(99B) The.Bedford.Incident.1965.1080p.BluRay.H264.AAC-RARBG.mp4(1.95GB)      ","magnet":"magnet:?xt=urn:btih:a41275265b81a4a649afcf58d487517440fd5a72&dn=The.Bedford.Incident.1965.1080p.BluRay.H264.AAC-RARBG&tr=http%3A%2F%2Ftracker.trackerfix.com%3A80%2Fannounce&tr=udp%3A%2F%2F9.rarbg.me%3A2780%2Fannounce&tr=udp%3A%2F%2F9.rarbg.to%3A2730%2Fannounce","img":"/Uploads/Picture/litpic/07/23Jul2015070106.jpg"},{"title":"布偶金银岛历险记 Muppet Treasure Island (1996)","name":"Muppet.Treasure.Island.1996.PROPER.1080p.BluRay.H264.AAC-RARBG","score":"","size":"1.9GB","date":"4天前","format":"BluRay-1080P","fileTree":"\n      Muppet.Treasure.Island.1996.PROPER.1080p.BluRay.H264.AAC-RARBG\n       Subs 2_English.srt(119.66KB) 3_English.srt(104.81KB) Muppet.Treasure.Island.1996.PROPER.1080p.BluRay.H264.AAC-RARBG.mp4(1.9GB) PianYuan.net.txt(30B) RARBG_DO_NOT_MIRROR.exe(99B)      ","magnet":"magnet:?xt=urn:btih:96b0acb5cfb6dad860939802fea27f379c307848&dn=Muppet.Treasure.Island.1996.PROPER.1080p.BluRay.H264.AAC-RARBG&tr=http%3A%2F%2Ftracker.trackerfix.com%3A80%2Fannounce&tr=udp%3A%2F%2F9.rarbg.me%3A2750%2Fannounce&tr=udp%3A%2F%2F9.rarbg.to%3A2740%2Fannounce","img":"/Uploads/Picture/litpic/07/21Jul2015192732.jpg"},{"title":"虞美人盛开的山坡 コクリコ坂から (2011)","name":"From.Up.On.Poppy.Hill.2011.DUBBED.PROPER.1080p.BluRay.H264.AAC-RARBG","score":"","size":"1.75GB","date":"4天前","format":"BluRay-1080P","fileTree":"\n      From.Up.On.Poppy.Hill.2011.DUBBED.PROPER.1080p.BluRay.H264.AAC-RARBG\n       From.Up.On.Poppy.Hill.2011.DUBBED.PROPER.1080p.BluRay.H264.AAC-RARBG.mp4(1.75GB) PianYuan.net.txt(30B) RARBG_DO_NOT_MIRROR.exe(99B)      ","magnet":"magnet:?xt=urn:btih:22777d3095a6e2d8dc556e62861cece3ef48c0a8&dn=From.Up.On.Poppy.Hill.2011.DUBBED.PROPER.1080p.BluRay.H264.AAC-RARBG&tr=http%3A%2F%2Ftracker.trackerfix.com%3A80%2Fannounce&tr=udp%3A%2F%2F9.rarbg.me%3A2730%2Fannounce&tr=udp%3A%2F%2F9.rarbg.to%3A2760%2Fannounce","img":"/Uploads/Picture/litpic/07/20Jul2015200942.jpg"},{"title":"鬼驱人 Poltergeist (2015)","name":"Poltergeist.2015.EXTENDED.PROPER.1080p.BluRay.H264.AAC-RARBG","score":"","size":"1.98GB","date":"4天前","format":"BluRay-1080P","fileTree":"\n      Poltergeist.2015.EXTENDED.PROPER.1080p.BluRay.H264.AAC-RARBG\n       Subs Poltergeist.2015.EXTENDED.PROPER.1080p.BluRay.H264.AAC-RARBG.idx(538.85KB) Poltergeist.2015.EXTENDED.PROPER.1080p.BluRay.H264.AAC-RARBG.sub(60.02MB) Poltergeist.2015.EXTENDED.PROPER.1080p.BluRay.H264.AAC-RARBG.mp4(1.92GB) PianYuan.net.txt(30B) RARBG_DO_NOT_MIRROR.exe(99B)      ","magnet":"magnet:?xt=urn:btih:230387883e6bf8e547b4a8390fb9fe2170250715&dn=Poltergeist.2015.EXTENDED.PROPER.1080p.BluRay.H264.AAC-RARBG&tr=http%3A%2F%2Ftracker.trackerfix.com%3A80%2Fannounce&tr=udp%3A%2F%2F9.rarbg.me%3A2770%2Fannounce&tr=udp%3A%2F%2F9.rarbg.to%3A2790%2Fannounce","img":"/Uploads/Picture/litpic/07/25Jul2015164827.jpg"},{"title":"领航员 Flight of the Navigator (1986)","name":"Flight.of.the.Navigator.1986.REMASTERED.1080p.BluRay.X264-AMIABLE","score":"","size":"8.75GB","date":"5天前","format":"BluRay-1080P","fileTree":"\n      Flight.of.the.Navigator.1986.REMASTERED.1080p.BluRay.X264-AMIABLE\n       Subs Flight.of.the.Navigator.1986.REMASTERED.1080p.BluRay.X264-AMIABLE.idx(53.16KB) Flight.of.the.Navigator.1986.REMASTERED.1080p.BluRay.X264-AMIABLE.sub(7.54MB) Flight.of.the.Navigator.1986.REMASTERED.1080p.BluRay.X264-AMIABLE.mkv(8.74GB) PianYuan.net.txt(30B) RARBG_DO_NOT_MIRROR.exe(99B) flight.of.the.navigator.1986.remastered.1080p.bluray.x264-amiable.nfo(1.43KB)      ","magnet":"magnet:?xt=urn:btih:9a3a5041fd4de72f6b83c673bfa15ca5a9fec0d6&dn=Flight.of.the.Navigator.1986.REMASTERED.1080p.BluRay.X264-AMIABLE&tr=http%3A%2F%2Ftracker.trackerfix.com%3A80%2Fannounce&tr=udp%3A%2F%2F9.rarbg.me%3A2750%2Fannounce&tr=udp%3A%2F%2F9.rarbg.to%3A2730%2Fannounce","img":"/Uploads/Picture/litpic/07/23Jul2015060520.jpg"},{"title":"One Soldier’s Story: The Journey of American Sniper One Soldier’s Story: The Journey of American Sniper (2015)","name":"One.Soldiers.Story.The.Journey.Of.American.Sniper.2015.1080p.BluRay.H264.AAC-RARBG","score":"","size":"646.72MB","date":"4天前","format":"BluRay-1080P","fileTree":"\n      One.Soldiers.Story.The.Journey.Of.American.Sniper.2015.1080p.BluRay.H264.AAC-RARBG\n       Subs One.Soldiers.Story.The.Journey.Of.American.Sniper.2015.1080p.BluRay.H264.AAC-RARBG.idx(186.31KB) One.Soldiers.Story.The.Journey.Of.American.Sniper.2015.1080p.BluRay.H264.AAC-RARBG.sub(40.11MB) One.Soldiers.Story.The.Journey.Of.American.Sniper.2015.1080p.BluRay.H264.AAC-RARBG.mp4(606.43MB) PianYuan.net.txt(30B) RARBG_DO_NOT_MIRROR.exe(99B)      ","magnet":"magnet:?xt=urn:btih:e1f68949c2b2e41a4488682984717f87c10d7068&dn=One.Soldiers.Story.The.Journey.Of.American.Sniper.2015.1080p.BluRay.H264.AAC-RARBG&tr=http%3A%2F%2Ftracker.trackerfix.com%3A80%2Fannounce&tr=udp%3A%2F%2F9.rarbg.me%3A2720%2Fannounce&tr=udp%3A%2F%2F9.rarbg.to%3A2730%2Fannounce","img":"/Uploads/Picture/litpic/08/21Aug2015205255.gif"},{"title":"冰崩 Ice Quake (2010)","name":"Ice.Quake.2010.PROPER.1080p.BluRay.H264.AAC-RARBG","score":"","size":"1.72GB","date":"4天前","format":"BluRay-1080P","fileTree":"\n      Ice.Quake.2010.PROPER.1080p.BluRay.H264.AAC-RARBG\n       Ice.Quake.2010.PROPER.1080p.BluRay.H264.AAC-RARBG.mp4(1.72GB) PianYuan.net.txt(30B) RARBG_DO_NOT_MIRROR.exe(99B)      ","magnet":"magnet:?xt=urn:btih:2be6d97990ac4b7eb15b16694015165196c253f2&dn=Ice.Quake.2010.PROPER.1080p.BluRay.H264.AAC-RARBG&tr=http%3A%2F%2Ftracker.trackerfix.com%3A80%2Fannounce&tr=udp%3A%2F%2F9.rarbg.me%3A2730%2Fannounce&tr=udp%3A%2F%2F9.rarbg.to%3A2720%2Fannounce","img":"/Uploads/Picture/litpic/07/20Jul2015223228.jpg"},{"title":"图像失真 De Artificiali Perspectiva (1991)","name":"Anamorphosis.1993.1080p.BluRay.H264.AAC-RARBG","score":"","size":"278.8MB","date":"4天前","format":"BluRay-1080P","fileTree":"\n      Anamorphosis.1993.1080p.BluRay.H264.AAC-RARBG\n       Anamorphosis.1993.1080p.BluRay.H264.AAC-RARBG.mp4(278.8MB) PianYuan.net.txt(30B) RARBG_DO_NOT_MIRROR.exe(99B)      ","magnet":"magnet:?xt=urn:btih:6afa797814a55087179a153b1435bf2a88c5a2fe&dn=Anamorphosis.1993.1080p.BluRay.H264.AAC-RARBG&tr=http%3A%2F%2Ftracker.trackerfix.com%3A80%2Fannounce&tr=udp%3A%2F%2F9.rarbg.me%3A2770%2Fannounce&tr=udp%3A%2F%2F9.rarbg.to%3A2780%2Fannounce","img":"/Uploads/Picture/litpic/02/08Feb2016102356.jpg"},{"title":"千尸屋 House of 1000 Corpses (2003)","name":"House.of.1000.Corpses.2003.PROPER.1080p.BluRay.H264.AAC-RARBG","score":"","size":"1.7GB","date":"4天前","format":"BluRay-1080P","fileTree":"\n      House.of.1000.Corpses.2003.PROPER.1080p.BluRay.H264.AAC-RARBG\n       Subs 2_English.srt(66.91KB) House.of.1000.Corpses.2003.PROPER.1080p.BluRay.H264.AAC-RARBG.mp4(1.7GB) PianYuan.net.txt(30B) RARBG_DO_NOT_MIRROR.exe(99B)      ","magnet":"magnet:?xt=urn:btih:03a4d26dfe140b63020866ca043b44cdb8676eec&dn=House.of.1000.Corpses.2003.PROPER.1080p.BluRay.H264.AAC-RARBG&tr=http%3A%2F%2Ftracker.trackerfix.com%3A80%2Fannounce&tr=udp%3A%2F%2F9.rarbg.me%3A2740%2Fannounce&tr=udp%3A%2F%2F9.rarbg.to%3A2730%2Fannounce","img":"/Uploads/Picture/litpic/07/22Jul2015080407.jpg"},{"title":"A Pure Country Gift A Pure Country Gift (2010)","name":"Pure.Country.2.The.Gift.2010.1080p.BluRay.H264.AAC-RARBG","score":"","size":"2.13GB","date":"4天前","format":"BluRay-1080P","fileTree":"\n      Pure.Country.2.The.Gift.2010.1080p.BluRay.H264.AAC-RARBG\n       Pure.Country.2.The.Gift.2010.1080p.BluRay.H264.AAC-RARBG.mp4(2.13GB) PianYuan.net.txt(30B) RARBG_DO_NOT_MIRROR.exe(99B)      ","magnet":"magnet:?xt=urn:btih:4b4889234ac39442cf35da17a46a4571db24adbf&dn=Pure.Country.2.The.Gift.2010.1080p.BluRay.H264.AAC-RARBG&tr=http%3A%2F%2Ftracker.trackerfix.com%3A80%2Fannounce&tr=udp%3A%2F%2F9.rarbg.me%3A2730%2Fannounce&tr=udp%3A%2F%2F9.rarbg.to%3A2750%2Fannounce","img":"/Uploads/Picture/litpic/07/23Jul2015005546.gif"}]